setup.cfg
setup.py
django_umeboshi.egg-info/PKG-INFO
django_umeboshi.egg-info/SOURCES.txt
django_umeboshi.egg-info/dependency_links.txt
django_umeboshi.egg-info/requires.txt
django_umeboshi.egg-info/top_level.txt
tests/__init__.py
tests/settings.py
tests/test.py
tests/urls.py
umeboshi/__init__.py
umeboshi/admin.py
umeboshi/apps.py
umeboshi/exceptions.py
umeboshi/models.py
umeboshi/routines.py
umeboshi/runner.py
umeboshi/tasks.py
umeboshi/triggers.py
umeboshi/utils.py
umeboshi/migrations/0001_initial.py
umeboshi/migrations/0002_auto_20151229_1537.py
umeboshi/migrations/__init__.py