Metadata-Version: 1.1
Name: django-umeboshi
Version: 0.4.1
Summary: Umeboshi is a Django application for durable long-term scheduling of arbitrary actions.
Home-page: https://github.com/makingspace/umeboshi
Author: MakeSpace Labs, Inc.
Author-email: zach.smith@makespace.com
License: Revised BSD
Platform: UNKNOWN
Classifier: Framework :: Django
Classifier: Intended Audience :: Developers
Classifier: License :: OSI Approved :: BSD License
Classifier: Operating System :: OS Independent
Classifier: Programming Language :: Python
Classifier: Topic :: Database
